{"game":{"appId":"eef3d0539f55422c9bef333d79c04e4c","name":"Ready or Not","capsuleUrl":"https://cdn1.epicgames.com/spt-assets/e2c3bc6771dc4524a4730b379f8242c7/ready-or-not-gu75g.png","shortDescription":"Ready or Not is an intense, tactical, first-person shooter that depicts a modern-day world in which SWAT police units are called to defuse hostile and confronting situations.","genres":"Open World, RPG, First Person","categories":"Multiplayer, Achievements, Controller Support","tags":null,"developers":"VOID Interactive Limited","publishers":"VOID Interactive Limited","releaseStatus":"RELEASED","releaseDate":"2025-07-15T07:00:00.000Z","releaseDateRaw":"2025-07-15T07:00:00.000Z","storeUrl":"https://store.epicgames.com/p/ready-or-not","slug":"ready-or-not"},"latest":{"currency":"USD","price":4999,"basePrice":4999,"discountPercent":0,"discountEnd":null,"recordedAt":"2026-01-18T18:08:11.122Z"},"history":[{"recordedAt":"2026-01-18T17:01:42.536Z","price":4999},{"recordedAt":"2026-01-18T17:20:19.325Z","price":4999},{"recordedAt":"2026-01-18T17:26:28.020Z","price":4999},{"recordedAt":"2026-01-18T17:36:31.848Z","price":4999},{"recordedAt":"2026-01-18T18:08:11.122Z","price":4999}]}