{"game":{"appId":"27f27fd7716d4df5bf55e158c0430679","name":"Wilder World - Super Early Access","capsuleUrl":"https://cdn1.epicgames.com/spt-assets/691bdcb1ffe944b980ec571558933baa/wilder-world-g1w4k.png","shortDescription":"Super Early Access is a pre-release that offers players early access to in-progress features. This phase allows players to explore, test and provide feedback on various game elements before the global launch of Wilder World.","genres":"RPG, 1인칭","categories":"업적, 데모","tags":null,"developers":"Wilder World","publishers":"CYPHER INC.","releaseStatus":"RELEASED","releaseDate":"2024-08-02T18:20:10.502Z","releaseDateRaw":"2024-08-02T18:20:10.502Z","storeUrl":"https://store.epicgames.com/p/wilder-world-alpha","slug":"wilder-world-alpha"},"latest":{"currency":"KRW","price":0,"basePrice":0,"discountPercent":0,"discountEnd":null,"recordedAt":"2026-01-18T16:46:02.640Z"},"history":[{"recordedAt":"2026-01-18T16:46:02.640Z","price":0}]}